syncservers/__init__.py
syncservers/app.py
syncservers/async_command.py
syncservers/async_task_queue.py
syncservers/config.py
syncservers/retry_queue.py
syncservers/sync_server.py
syncservers/syncs.py
syncservers-1.0.1.dist-info/LICENSE.MD
syncservers-1.0.1.dist-info/METADATA
syncservers-1.0.1.dist-info/WHEEL
syncservers-1.0.1.dist-info/top_level.txt
syncservers-1.0.1.dist-info/RECORD
