Metadata-Version: 2.1
Name: syncservers
Version: 1.0.1
Summary: instantly sync data among home servers
Author-email: Zhuo Wang <zhuowang10@gmail.com>
Project-URL: Homepage, https://github.com/zhuowang10/syncservers
Classifier: Programming Language :: Python :: 3
Classifier: License :: OSI Approved :: MIT License
Classifier: Operating System :: OS Independent
Requires-Python: <4,>=3.7
License-File: LICENSE.MD
Requires-Dist: asyncinotify >=4.2.0
Requires-Dist: asynclcron >=1.0.0
